envsub-0.2.1.dist-info/METADATA
envsub-0.2.1.dist-info/WHEEL
envsub-0.2.1.dist-info/entry_points.txt
envsub-0.2.1.dist-info/licenses/LICENSE
envsub/envsub.pyi
envsub/py.typed
envsub/__init__.py
envsub/__main__.py
envsub/envsub.cp312-win_amd64.pyd
envsub-0.2.1.dist-info/RECORD
