Metadata-Version: 2.4
Name: envsub
Version: 0.2.1
Classifier: License :: OSI Approved :: MIT License
Classifier: Programming Language :: Python :: 3
Classifier: Programming Language :: Rust
Classifier: Topic :: Software Development :: Libraries :: Python Modules
Classifier: Topic :: Text Processing
Classifier: Typing :: Typed
Requires-Dist: furo>=2024.5.6 ; extra == 'docs'
Requires-Dist: linkify-it-py>=2.0.3,<3 ; extra == 'docs'
Requires-Dist: myst-parser>=3.0.0,<4 ; python_full_version < '3.10' and extra == 'docs'
Requires-Dist: myst-parser>=4.0.0,<5 ; python_full_version >= '3.10' and extra == 'docs'
Requires-Dist: sphinx>=7.0.1,<8 ; extra == 'docs'
Requires-Dist: sphinx-autodoc2>=0.5.0,<1 ; extra == 'docs'
Provides-Extra: docs
License-File: LICENSE
Summary: A text preprocessing tool with environment variable substitution.
Keywords: environment,substitution,variables
Author: Guillaume Gauvrit <guillaume@gauvr.it>
Author-email: Guillaume Gauvrit <guillaume@gauvr.it>
License: MIT
Requires-Python: >=3.9
Project-URL: Homepage, https://github.com/mardiros/envsub/
Project-URL: Documentation, https://mardiros.github.io/envsub/
Project-URL: Repository, https://github.com/mardiros/envsub.git
Project-URL: Issues, https://github.com/mardiros/envsub/issues
Project-URL: Changelog, https://mardiros.github.io/envsub/changelog.html
